CHANGES.rst
CONTRIBUTORS.rst
MANIFEST.in
README.rst
setup.cfg
setup.py
docs/LICENSE.GPL
docs/LICENSE.txt
docs/newsticker.png
docs/stock_ticker.png
src/collective/__init__.py
src/collective.newsticker.egg-info/PKG-INFO
src/collective.newsticker.egg-info/SOURCES.txt
src/collective.newsticker.egg-info/dependency_links.txt
src/collective.newsticker.egg-info/entry_points.txt
src/collective.newsticker.egg-info/namespace_packages.txt
src/collective.newsticker.egg-info/not-zip-safe
src/collective.newsticker.egg-info/requires.txt
src/collective.newsticker.egg-info/top_level.txt
src/collective/newsticker/__init__.py
src/collective/newsticker/config.py
src/collective/newsticker/configure.zcml
src/collective/newsticker/controlpanel.py
src/collective/newsticker/interfaces.py
src/collective/newsticker/profiles.zcml
src/collective/newsticker/setuphandlers.py
src/collective/newsticker/testing.py
src/collective/newsticker/vocabulary.py
src/collective/newsticker/Extensions/Install.py
src/collective/newsticker/Extensions/__init__.py
src/collective/newsticker/browser/__init__.py
src/collective/newsticker/browser/configure.zcml
src/collective/newsticker/browser/newsticker_viewlet.pt
src/collective/newsticker/browser/static/controls.png
src/collective/newsticker/browser/static/newsticker-icon.png
src/collective/newsticker/browser/static/newsticker.css
src/collective/newsticker/browser/static/newsticker.css.map
src/collective/newsticker/browser/static/newsticker.js
src/collective/newsticker/browser/static/newsticker.js.map
src/collective/newsticker/locales/collective.newsticker.pot
src/collective/newsticker/locales/manual.pot
src/collective/newsticker/locales/plone.pot
src/collective/newsticker/locales/es/LC_MESSAGES/collective.newsticker.po
src/collective/newsticker/locales/es/LC_MESSAGES/plone.po
src/collective/newsticker/locales/pt_BR/LC_MESSAGES/collective.newsticker.po
src/collective/newsticker/locales/pt_BR/LC_MESSAGES/plone.po
src/collective/newsticker/profiles/default/browserlayer.xml
src/collective/newsticker/profiles/default/controlpanel.xml
src/collective/newsticker/profiles/default/cssregistry.xml
src/collective/newsticker/profiles/default/jsregistry.xml
src/collective/newsticker/profiles/default/metadata.xml
src/collective/newsticker/profiles/default/registry.xml
src/collective/newsticker/profiles/default/rolemap.xml
