Metadata-Version: 2.1
Name: collective.newsticker
Version: 2.1b2
Summary: A horizontal, text-based display dedicated to presenting headlines on a site.
Home-page: https://github.com/collective/collective.newsticker
Author: Hector Velarde
Author-email: hector.velarde@gmail.com
License: UNKNOWN
Keywords: plone jquery news ticker
Platform: UNKNOWN
Classifier: Development Status :: 4 - Beta
Classifier: Environment :: Web Environment
Classifier: Framework :: Plone
Classifier: Framework :: Plone :: 4.2
Classifier: Framework :: Plone :: 4.3
Classifier: Framework :: Plone :: 5.0
Classifier: Framework :: Plone :: 5.1
Classifier: Intended Audience :: System Administrators
Classifier: License :: OSI Approved :: GNU General Public License v2 (GPLv2)
Classifier: Operating System :: OS Independent
Classifier: Programming Language :: JavaScript
Classifier: Programming Language :: Python
Classifier: Programming Language :: Python :: 2.7
Classifier: Topic :: Office/Business :: News/Diary
Classifier: Topic :: Software Development :: Libraries :: Python Modules
Provides-Extra: test
